{
 "fastgo": [
  {
   "Case": "fastgo",
   "Workers": 20,
   "ChanLen": 10000,
   "Amount": 300,
   "Spent": 1487066,
   "AllocBytes": 343728,
   "AllocObjects": 1391,
   "AllocBytesTotal": 343728,
   "SystemMem": 262144
  },
  {
   "Case": "fastgo",
   "Workers": 20,
   "ChanLen": 10000,
   "Amount": 3000,
   "Spent": 9549370,
   "AllocBytes": 2275504,
   "AllocObjects": 9763,
   "AllocBytesTotal": 2275504,
   "SystemMem": 524288
  },
  {
   "Case": "fastgo",
   "Workers": 20,
   "ChanLen": 10000,
   "Amount": 30000,
   "Spent": 93054600,
   "AllocBytes": 11642928,
   "AllocObjects": 87554,
   "AllocBytesTotal": 19646920,
   "SystemMem": 2357496
  },
  {
   "Case": "fastgo",
   "Workers": 20,
   "ChanLen": 10000,
   "Amount": 300000,
   "Spent": 867905570,
   "AllocBytes": 34281824,
   "AllocObjects": 670067,
   "AllocBytesTotal": 139308920,
   "SystemMem": 70453248
  },
  {
   "Case": "fastgo",
   "Workers": 20,
   "ChanLen": 10000,
   "Amount": 1000000,
   "Spent": 2864529027,
   "AllocBytes": 37762224,
   "AllocObjects": 2108169,
   "AllocBytesTotal": 427306424,
   "SystemMem": 72351992
  },
  {
   "Case": "fastgo",
   "Workers": 20,
   "ChanLen": 10000,
   "Amount": 3000000,
   "Spent": 9559245608,
   "AllocBytes": 39193744,
   "AllocObjects": 6295676,
   "AllocBytesTotal": 1259164192,
   "SystemMem": 72614136
  },
  {
   "Case": "fastgo",
   "Workers": 20,
   "ChanLen": 10000,
   "Amount": 10000000,
   "Spent": 41020846827,
   "AllocBytes": 46222928,
   "AllocObjects": 20889195,
   "AllocBytesTotal": 4158680568,
   "SystemMem": 72974584
  }
 ],
 "fastpool": [
  {
   "Case": "fastpool",
   "Workers": 20,
   "ChanLen": 10000,
   "Amount": 300,
   "Spent": 458642,
   "AllocBytes": 220672,
   "AllocObjects": 1091,
   "AllocBytesTotal": 220672,
   "SystemMem": 1702136
  },
  {
   "Case": "fastpool",
   "Workers": 20,
   "ChanLen": 10000,
   "Amount": 3000,
   "Spent": 4029824,
   "AllocBytes": 1820704,
   "AllocObjects": 8869,
   "AllocBytesTotal": 1820704,
   "SystemMem": 0
  },
  {
   "Case": "fastpool",
   "Workers": 20,
   "ChanLen": 10000,
   "Amount": 30000,
   "Spent": 27743262,
   "AllocBytes": 5618544,
   "AllocObjects": 80694,
   "AllocBytesTotal": 16291992,
   "SystemMem": 2357496
  },
  {
   "Case": "fastpool",
   "Workers": 20,
   "ChanLen": 10000,
   "Amount": 300000,
   "Spent": 225120231,
   "AllocBytes": 8026672,
   "AllocObjects": 622742,
   "AllocBytesTotal": 121030192,
   "SystemMem": 917504
  },
  {
   "Case": "fastpool",
   "Workers": 20,
   "ChanLen": 10000,
   "Amount": 1000000,
   "Spent": 725830492,
   "AllocBytes": 6302464,
   "AllocObjects": 2028091,
   "AllocBytesTotal": 391715184,
   "SystemMem": 2357496
  },
  {
   "Case": "fastpool",
   "Workers": 20,
   "ChanLen": 10000,
   "Amount": 3000000,
   "Spent": 2464374729,
   "AllocBytes": 5846864,
   "AllocObjects": 6042632,
   "AllocBytesTotal": 1165394360,
   "SystemMem": 917504
  },
  {
   "Case": "fastpool",
   "Workers": 20,
   "ChanLen": 10000,
   "Amount": 10000000,
   "Spent": 11776804703,
   "AllocBytes": 6834864,
   "AllocObjects": 20100390,
   "AllocBytesTotal": 3891297248,
   "SystemMem": 2357496
  }
 ],
 "go": [
  {
   "Case": "go",
   "Workers": 20,
   "ChanLen": 10000,
   "Amount": 300,
   "Spent": 1972330,
   "AllocBytes": 435656,
   "AllocObjects": 3005,
   "AllocBytesTotal": 435656,
   "SystemMem": 524288
  },
  {
   "Case": "go",
   "Workers": 20,
   "ChanLen": 10000,
   "Amount": 3000,
   "Spent": 15241921,
   "AllocBytes": 3526328,
   "AllocObjects": 27334,
   "AllocBytesTotal": 3778440,
   "SystemMem": 589824
  },
  {
   "Case": "go",
   "Workers": 20,
   "ChanLen": 10000,
   "Amount": 30000,
   "Spent": 156975584,
   "AllocBytes": 11694024,
   "AllocObjects": 231687,
   "AllocBytesTotal": 26110752,
   "SystemMem": 917504
  },
  {
   "Case": "go",
   "Workers": 20,
   "ChanLen": 10000,
   "Amount": 300000,
   "Spent": 1322121716,
   "AllocBytes": 31676816,
   "AllocObjects": 2183141,
   "AllocBytesTotal": 221780544,
   "SystemMem": 71827704
  },
  {
   "Case": "go",
   "Workers": 20,
   "ChanLen": 10000,
   "Amount": 1000000,
   "Spent": 4265565242,
   "AllocBytes": 50136136,
   "AllocObjects": 7211069,
   "AllocBytesTotal": 713676040,
   "SystemMem": 72974584
  },
  {
   "Case": "go",
   "Workers": 20,
   "ChanLen": 10000,
   "Amount": 3000000,
   "Spent": 16086298673,
   "AllocBytes": 35353864,
   "AllocObjects": 21433171,
   "AllocBytesTotal": 2081013096,
   "SystemMem": 71174144
  },
  {
   "Case": "go",
   "Workers": 20,
   "ChanLen": 10000,
   "Amount": 10000000,
   "Spent": 64786864069,
   "AllocBytes": 32976448,
   "AllocObjects": 71174968,
   "AllocBytesTotal": 6891803120,
   "SystemMem": 141920504
  }
 ],
 "pool": [
  {
   "Case": "pool",
   "Workers": 20,
   "ChanLen": 10000,
   "Amount": 300,
   "Spent": 949513,
   "AllocBytes": 348752,
   "AllocObjects": 2932,
   "AllocBytesTotal": 348752,
   "SystemMem": 2226424
  },
  {
   "Case": "pool",
   "Workers": 20,
   "ChanLen": 10000,
   "Amount": 3000,
   "Spent": 9853523,
   "AllocBytes": 2924560,
   "AllocObjects": 26206,
   "AllocBytesTotal": 3139800,
   "SystemMem": 2291960
  },
  {
   "Case": "pool",
   "Workers": 20,
   "ChanLen": 10000,
   "Amount": 30000,
   "Spent": 73369700,
   "AllocBytes": 8998168,
   "AllocObjects": 230456,
   "AllocBytesTotal": 24446552,
   "SystemMem": 2357496
  },
  {
   "Case": "pool",
   "Workers": 20,
   "ChanLen": 10000,
   "Amount": 300000,
   "Spent": 581284265,
   "AllocBytes": 10334080,
   "AllocObjects": 2135904,
   "AllocBytesTotal": 207738400,
   "SystemMem": 917504
  },
  {
   "Case": "pool",
   "Workers": 20,
   "ChanLen": 10000,
   "Amount": 1000000,
   "Spent": 2076150691,
   "AllocBytes": 8936240,
   "AllocObjects": 7054753,
   "AllocBytesTotal": 679010232,
   "SystemMem": 917504
  },
  {
   "Case": "pool",
   "Workers": 20,
   "ChanLen": 10000,
   "Amount": 3000000,
   "Spent": 7268576035,
   "AllocBytes": 9771528,
   "AllocObjects": 21120576,
   "AllocBytesTotal": 2024805680,
   "SystemMem": 2357496
  },
  {
   "Case": "pool",
   "Workers": 20,
   "ChanLen": 10000,
   "Amount": 10000000,
   "Spent": 24807451866,
   "AllocBytes": 14031168,
   "AllocObjects": 70360936,
   "AllocBytesTotal": 6741207168,
   "SystemMem": 2357496
  }
 ]
}
