{
 "fastgo": [
  {
   "Case": "fastgo",
   "Workers": 20,
   "ChanLen": 10000,
   "Amount": 30,
   "SpentMs": 343152,
   "AllocBytes": 52656,
   "AllocObjects": 229,
   "AllocBytesTotal": 52656,
   "SystemMem": 0,
   "NoGC": false
  },
  {
   "Case": "fastgo",
   "Workers": 20,
   "ChanLen": 10000,
   "Amount": 100,
   "SpentMs": 431938,
   "AllocBytes": 130816,
   "AllocObjects": 547,
   "AllocBytesTotal": 130816,
   "SystemMem": 262144,
   "NoGC": false
  },
  {
   "Case": "fastgo",
   "Workers": 20,
   "ChanLen": 10000,
   "Amount": 300,
   "SpentMs": 1273000,
   "AllocBytes": 314448,
   "AllocObjects": 1262,
   "AllocBytesTotal": 314448,
   "SystemMem": 262144,
   "NoGC": false
  },
  {
   "Case": "fastgo",
   "Workers": 20,
   "ChanLen": 10000,
   "Amount": 1000,
   "SpentMs": 2048880,
   "AllocBytes": 692128,
   "AllocObjects": 2936,
   "AllocBytesTotal": 692128,
   "SystemMem": 786432,
   "NoGC": false
  },
  {
   "Case": "fastgo",
   "Workers": 20,
   "ChanLen": 10000,
   "Amount": 3000,
   "SpentMs": 8921959,
   "AllocBytes": 1574608,
   "AllocObjects": 7321,
   "AllocBytesTotal": 1574608,
   "SystemMem": 2488568,
   "NoGC": false
  },
  {
   "Case": "fastgo",
   "Workers": 20,
   "ChanLen": 10000,
   "Amount": 10000,
   "SpentMs": 14251932,
   "AllocBytes": 2692288,
   "AllocObjects": 24352,
   "AllocBytesTotal": 5036432,
   "SystemMem": 3406072,
   "NoGC": false
  },
  {
   "Case": "fastgo",
   "Workers": 20,
   "ChanLen": 10000,
   "Amount": 30000,
   "SpentMs": 40460776,
   "AllocBytes": 1365704,
   "AllocObjects": 67514,
   "AllocBytesTotal": 13293448,
   "SystemMem": 3668216,
   "NoGC": false
  },
  {
   "Case": "fastgo",
   "Workers": 20,
   "ChanLen": 10000,
   "Amount": 100000,
   "SpentMs": 122538191,
   "AllocBytes": 1156096,
   "AllocObjects": 206696,
   "AllocBytesTotal": 39949856,
   "SystemMem": 1703936,
   "NoGC": false
  }
 ],
 "fastpool": [
  {
   "Case": "fastpool",
   "Workers": 20,
   "ChanLen": 10000,
   "Amount": 30,
   "SpentMs": 398706,
   "AllocBytes": 35760,
   "AllocObjects": 173,
   "AllocBytesTotal": 35760,
   "SystemMem": 0,
   "NoGC": false
  },
  {
   "Case": "fastpool",
   "Workers": 20,
   "ChanLen": 10000,
   "Amount": 100,
   "SpentMs": 368709,
   "AllocBytes": 106576,
   "AllocObjects": 518,
   "AllocBytesTotal": 106576,
   "SystemMem": 0,
   "NoGC": false
  },
  {
   "Case": "fastpool",
   "Workers": 20,
   "ChanLen": 10000,
   "Amount": 300,
   "SpentMs": 516706,
   "AllocBytes": 262752,
   "AllocObjects": 1274,
   "AllocBytesTotal": 262752,
   "SystemMem": 1702136,
   "NoGC": false
  },
  {
   "Case": "fastpool",
   "Workers": 20,
   "ChanLen": 10000,
   "Amount": 1000,
   "SpentMs": 1207357,
   "AllocBytes": 692432,
   "AllocObjects": 3386,
   "AllocBytesTotal": 692432,
   "SystemMem": 1964280,
   "NoGC": false
  },
  {
   "Case": "fastpool",
   "Workers": 20,
   "ChanLen": 10000,
   "Amount": 3000,
   "SpentMs": 3373426,
   "AllocBytes": 1767840,
   "AllocObjects": 8714,
   "AllocBytesTotal": 1767840,
   "SystemMem": 2226424,
   "NoGC": false
  },
  {
   "Case": "fastpool",
   "Workers": 20,
   "ChanLen": 10000,
   "Amount": 10000,
   "SpentMs": 11926074,
   "AllocBytes": 1736640,
   "AllocObjects": 26359,
   "AllocBytesTotal": 5276208,
   "SystemMem": 3143928,
   "NoGC": false
  },
  {
   "Case": "fastpool",
   "Workers": 20,
   "ChanLen": 10000,
   "Amount": 30000,
   "SpentMs": 34009636,
   "AllocBytes": 7908592,
   "AllocObjects": 81019,
   "AllocBytesTotal": 16367904,
   "SystemMem": 3930360,
   "NoGC": false
  },
  {
   "Case": "fastpool",
   "Workers": 20,
   "ChanLen": 10000,
   "Amount": 100000,
   "SpentMs": 114534640,
   "AllocBytes": 5992496,
   "AllocObjects": 222162,
   "AllocBytesTotal": 43518672,
   "SystemMem": 3930360,
   "NoGC": false
  }
 ],
 "go": [
  {
   "Case": "go",
   "Workers": 20,
   "ChanLen": 10000,
   "Amount": 30,
   "SpentMs": 350746,
   "AllocBytes": 55000,
   "AllocObjects": 387,
   "AllocBytesTotal": 55000,
   "SystemMem": 262144,
   "NoGC": false
  },
  {
   "Case": "go",
   "Workers": 20,
   "ChanLen": 10000,
   "Amount": 100,
   "SpentMs": 498392,
   "AllocBytes": 148200,
   "AllocObjects": 1030,
   "AllocBytesTotal": 148200,
   "SystemMem": 262144,
   "NoGC": false
  },
  {
   "Case": "go",
   "Workers": 20,
   "ChanLen": 10000,
   "Amount": 300,
   "SpentMs": 1022161,
   "AllocBytes": 390312,
   "AllocObjects": 2801,
   "AllocBytesTotal": 390312,
   "SystemMem": 786432,
   "NoGC": false
  },
  {
   "Case": "go",
   "Workers": 20,
   "ChanLen": 10000,
   "Amount": 1000,
   "SpentMs": 2198260,
   "AllocBytes": 999280,
   "AllocObjects": 8141,
   "AllocBytesTotal": 999280,
   "SystemMem": 2750712,
   "NoGC": false
  },
  {
   "Case": "go",
   "Workers": 20,
   "ChanLen": 10000,
   "Amount": 3000,
   "SpentMs": 6045351,
   "AllocBytes": 2578344,
   "AllocObjects": 24006,
   "AllocBytesTotal": 2832976,
   "SystemMem": 3078392,
   "NoGC": false
  },
  {
   "Case": "go",
   "Workers": 20,
   "ChanLen": 10000,
   "Amount": 10000,
   "SpentMs": 20503048,
   "AllocBytes": 2974056,
   "AllocObjects": 74264,
   "AllocBytesTotal": 7696616,
   "SystemMem": 1966080,
   "NoGC": false
  },
  {
   "Case": "go",
   "Workers": 20,
   "ChanLen": 10000,
   "Amount": 30000,
   "SpentMs": 54778301,
   "AllocBytes": 2598736,
   "AllocObjects": 219485,
   "AllocBytesTotal": 21996968,
   "SystemMem": 2752512,
   "NoGC": false
  },
  {
   "Case": "go",
   "Workers": 20,
   "ChanLen": 10000,
   "Amount": 100000,
   "SpentMs": 162868184,
   "AllocBytes": 2761304,
   "AllocObjects": 713913,
   "AllocBytesTotal": 68440688,
   "SystemMem": 2555904,
   "NoGC": false
  }
 ],
 "goweb": [
  {
   "Case": "goweb",
   "Workers": 20,
   "ChanLen": 10000,
   "Amount": 30,
   "SpentMs": 23031464,
   "AllocBytes": 699160,
   "AllocObjects": 3862,
   "AllocBytesTotal": 699160,
   "SystemMem": 1835008,
   "NoGC": false
  },
  {
   "Case": "goweb",
   "Workers": 20,
   "ChanLen": 10000,
   "Amount": 100,
   "SpentMs": 22713550,
   "AllocBytes": 1007888,
   "AllocObjects": 11461,
   "AllocBytesTotal": 1854792,
   "SystemMem": 1638400,
   "NoGC": false
  },
  {
   "Case": "goweb",
   "Workers": 20,
   "ChanLen": 10000,
   "Amount": 300,
   "SpentMs": 55752441,
   "AllocBytes": 5286720,
   "AllocObjects": 35966,
   "AllocBytesTotal": 6759600,
   "SystemMem": 3014656,
   "NoGC": false
  },
  {
   "Case": "goweb",
   "Workers": 20,
   "ChanLen": 10000,
   "Amount": 1000,
   "SpentMs": 110211525,
   "AllocBytes": 21141008,
   "AllocObjects": 125025,
   "AllocBytesTotal": 24953008,
   "SystemMem": 4520184,
   "NoGC": false
  },
  {
   "Case": "goweb",
   "Workers": 20,
   "ChanLen": 10000,
   "Amount": 3000,
   "SpentMs": 266565940,
   "AllocBytes": 59366376,
   "AllocObjects": 373698,
   "AllocBytesTotal": 74332648,
   "SystemMem": 74744056,
   "NoGC": false
  },
  {
   "Case": "goweb",
   "Workers": 20,
   "ChanLen": 10000,
   "Amount": 10000,
   "SpentMs": 584195947,
   "AllocBytes": 190931824,
   "AllocObjects": 1196993,
   "AllocBytesTotal": 229280576,
   "SystemMem": 358252792,
   "NoGC": false
  },
  {
   "Case": "goweb",
   "Workers": 20,
   "ChanLen": 10000,
   "Amount": 30000,
   "SpentMs": 4529921517,
   "AllocBytes": 617769280,
   "AllocObjects": 3814160,
   "AllocBytesTotal": 711235528,
   "SystemMem": 858832120,
   "NoGC": false
  },
  {
   "Case": "goweb",
   "Workers": 20,
   "ChanLen": 10000,
   "Amount": 100000,
   "SpentMs": 187715176020,
   "AllocBytes": 790051960,
   "AllocObjects": 14669344,
   "AllocBytesTotal": 1791268848,
   "SystemMem": 2200410368,
   "NoGC": false
  }
 ],
 "pool": [
  {
   "Case": "pool",
   "Workers": 20,
   "ChanLen": 10000,
   "Amount": 30,
   "SpentMs": 363440,
   "AllocBytes": 49160,
   "AllocObjects": 429,
   "AllocBytesTotal": 49160,
   "SystemMem": 262144,
   "NoGC": false
  },
  {
   "Case": "pool",
   "Workers": 20,
   "ChanLen": 10000,
   "Amount": 100,
   "SpentMs": 570226,
   "AllocBytes": 127560,
   "AllocObjects": 1072,
   "AllocBytesTotal": 127560,
   "SystemMem": 262144,
   "NoGC": false
  },
  {
   "Case": "pool",
   "Workers": 20,
   "ChanLen": 10000,
   "Amount": 300,
   "SpentMs": 793383,
   "AllocBytes": 353800,
   "AllocObjects": 2894,
   "AllocBytesTotal": 353800,
   "SystemMem": 262144,
   "NoGC": false
  },
  {
   "Case": "pool",
   "Workers": 20,
   "ChanLen": 10000,
   "Amount": 1000,
   "SpentMs": 1367116,
   "AllocBytes": 972968,
   "AllocObjects": 8560,
   "AllocBytesTotal": 972968,
   "SystemMem": 2488568,
   "NoGC": false
  },
  {
   "Case": "pool",
   "Workers": 20,
   "ChanLen": 10000,
   "Amount": 3000,
   "SpentMs": 9857948,
   "AllocBytes": 2261224,
   "AllocObjects": 23877,
   "AllocBytesTotal": 2576232,
   "SystemMem": 2554104,
   "NoGC": false
  },
  {
   "Case": "pool",
   "Workers": 20,
   "ChanLen": 10000,
   "Amount": 10000,
   "SpentMs": 14625952,
   "AllocBytes": 3400720,
   "AllocObjects": 73406,
   "AllocBytesTotal": 7260904,
   "SystemMem": 3406072,
   "NoGC": false
  },
  {
   "Case": "pool",
   "Workers": 20,
   "ChanLen": 10000,
   "Amount": 30000,
   "SpentMs": 33338743,
   "AllocBytes": 1643360,
   "AllocObjects": 213990,
   "AllocBytesTotal": 20401352,
   "SystemMem": 3930360,
   "NoGC": false
  },
  {
   "Case": "pool",
   "Workers": 20,
   "ChanLen": 10000,
   "Amount": 100000,
   "SpentMs": 99665345,
   "AllocBytes": 2034744,
   "AllocObjects": 714262,
   "AllocBytesTotal": 68185304,
   "SystemMem": 3930360,
   "NoGC": false
  }
 ],
 "poolweb": [
  {
   "Case": "poolweb",
   "Workers": 20,
   "ChanLen": 10000,
   "Amount": 30,
   "SpentMs": 26377920,
   "AllocBytes": 722568,
   "AllocObjects": 3984,
   "AllocBytesTotal": 722568,
   "SystemMem": 3012856,
   "NoGC": false
  },
  {
   "Case": "poolweb",
   "Workers": 20,
   "ChanLen": 10000,
   "Amount": 100,
   "SpentMs": 28671758,
   "AllocBytes": 989744,
   "AllocObjects": 10775,
   "AllocBytesTotal": 1768016,
   "SystemMem": 3864824,
   "NoGC": false
  },
  {
   "Case": "poolweb",
   "Workers": 20,
   "ChanLen": 10000,
   "Amount": 300,
   "SpentMs": 32663930,
   "AllocBytes": 1763104,
   "AllocObjects": 28418,
   "AllocBytesTotal": 3950624,
   "SystemMem": 3668216,
   "NoGC": false
  },
  {
   "Case": "poolweb",
   "Workers": 20,
   "ChanLen": 10000,
   "Amount": 1000,
   "SpentMs": 45891999,
   "AllocBytes": 1941928,
   "AllocObjects": 89782,
   "AllocBytesTotal": 11434040,
   "SystemMem": 4454648,
   "NoGC": false
  },
  {
   "Case": "poolweb",
   "Workers": 20,
   "ChanLen": 10000,
   "Amount": 3000,
   "SpentMs": 93373690,
   "AllocBytes": 1580936,
   "AllocObjects": 273219,
   "AllocBytesTotal": 34730008,
   "SystemMem": 4454648,
   "NoGC": false
  },
  {
   "Case": "poolweb",
   "Workers": 20,
   "ChanLen": 10000,
   "Amount": 10000,
   "SpentMs": 249487905,
   "AllocBytes": 1011128,
   "AllocObjects": 903019,
   "AllocBytesTotal": 113139944,
   "SystemMem": 4454648,
   "NoGC": false
  },
  {
   "Case": "poolweb",
   "Workers": 20,
   "ChanLen": 10000,
   "Amount": 30000,
   "SpentMs": 1069338515,
   "AllocBytes": 1585592,
   "AllocObjects": 2677516,
   "AllocBytesTotal": 332708472,
   "SystemMem": 3014656,
   "NoGC": false
  },
  {
   "Case": "poolweb",
   "Workers": 20,
   "ChanLen": 10000,
   "Amount": 100000,
   "SpentMs": 3006893254,
   "AllocBytes": 1342392,
   "AllocObjects": 8957204,
   "AllocBytesTotal": 1120477736,
   "SystemMem": 4454648,
   "NoGC": false
  }
 ]
}
