{
 "fastgo": [
  {
   "Case": "fastgo",
   "Workers": 20,
   "ChanLen": 10000,
   "Amount": 30,
   "SpentMs": 343795,
   "AllocBytes": 52240,
   "AllocObjects": 224,
   "AllocBytesTotal": 52240,
   "SystemMem": 262144,
   "NoGC": false
  },
  {
   "Case": "fastgo",
   "Workers": 20,
   "ChanLen": 10000,
   "Amount": 100,
   "SpentMs": 492103,
   "AllocBytes": 142192,
   "AllocObjects": 597,
   "AllocBytesTotal": 142192,
   "SystemMem": 262144,
   "NoGC": false
  },
  {
   "Case": "fastgo",
   "Workers": 20,
   "ChanLen": 10000,
   "Amount": 300,
   "SpentMs": 972805,
   "AllocBytes": 294800,
   "AllocObjects": 1170,
   "AllocBytesTotal": 294800,
   "SystemMem": 262144,
   "NoGC": false
  },
  {
   "Case": "fastgo",
   "Workers": 20,
   "ChanLen": 10000,
   "Amount": 1000,
   "SpentMs": 1643994,
   "AllocBytes": 709040,
   "AllocObjects": 2972,
   "AllocBytesTotal": 709040,
   "SystemMem": 786432,
   "NoGC": false
  },
  {
   "Case": "fastgo",
   "Workers": 20,
   "ChanLen": 10000,
   "Amount": 3000,
   "SpentMs": 4206954,
   "AllocBytes": 1483968,
   "AllocObjects": 6982,
   "AllocBytesTotal": 1483968,
   "SystemMem": 2226424,
   "NoGC": false
  },
  {
   "Case": "fastgo",
   "Workers": 20,
   "ChanLen": 10000,
   "Amount": 10000,
   "SpentMs": 12612941,
   "AllocBytes": 2298368,
   "AllocObjects": 22316,
   "AllocBytesTotal": 4474968,
   "SystemMem": 3340536,
   "NoGC": false
  }
 ],
 "fastpool": [
  {
   "Case": "fastpool",
   "Workers": 20,
   "ChanLen": 10000,
   "Amount": 30,
   "SpentMs": 381596,
   "AllocBytes": 44640,
   "AllocObjects": 222,
   "AllocBytesTotal": 44640,
   "SystemMem": 0,
   "NoGC": false
  },
  {
   "Case": "fastpool",
   "Workers": 20,
   "ChanLen": 10000,
   "Amount": 100,
   "SpentMs": 410881,
   "AllocBytes": 104736,
   "AllocObjects": 514,
   "AllocBytesTotal": 104736,
   "SystemMem": 262144,
   "NoGC": false
  },
  {
   "Case": "fastpool",
   "Workers": 20,
   "ChanLen": 10000,
   "Amount": 300,
   "SpentMs": 540383,
   "AllocBytes": 248032,
   "AllocObjects": 1208,
   "AllocBytesTotal": 248032,
   "SystemMem": 262144,
   "NoGC": false
  },
  {
   "Case": "fastpool",
   "Workers": 20,
   "ChanLen": 10000,
   "Amount": 1000,
   "SpentMs": 1425494,
   "AllocBytes": 664272,
   "AllocObjects": 3266,
   "AllocBytesTotal": 664272,
   "SystemMem": 524288,
   "NoGC": false
  },
  {
   "Case": "fastpool",
   "Workers": 20,
   "ChanLen": 10000,
   "Amount": 3000,
   "SpentMs": 3781489,
   "AllocBytes": 1840704,
   "AllocObjects": 9006,
   "AllocBytesTotal": 1840704,
   "SystemMem": 2226424,
   "NoGC": false
  },
  {
   "Case": "fastpool",
   "Workers": 20,
   "ChanLen": 10000,
   "Amount": 10000,
   "SpentMs": 12636493,
   "AllocBytes": 3137120,
   "AllocObjects": 29063,
   "AllocBytesTotal": 5915776,
   "SystemMem": 3930360,
   "NoGC": false
  }
 ],
 "go": [
  {
   "Case": "go",
   "Workers": 20,
   "ChanLen": 10000,
   "Amount": 30,
   "SpentMs": 294753,
   "AllocBytes": 55304,
   "AllocObjects": 389,
   "AllocBytesTotal": 55304,
   "SystemMem": 0,
   "NoGC": false
  },
  {
   "Case": "go",
   "Workers": 20,
   "ChanLen": 10000,
   "Amount": 100,
   "SpentMs": 532318,
   "AllocBytes": 159768,
   "AllocObjects": 1106,
   "AllocBytesTotal": 159768,
   "SystemMem": 524288,
   "NoGC": false
  },
  {
   "Case": "go",
   "Workers": 20,
   "ChanLen": 10000,
   "Amount": 300,
   "SpentMs": 1125872,
   "AllocBytes": 387336,
   "AllocObjects": 2765,
   "AllocBytesTotal": 387336,
   "SystemMem": 1964280,
   "NoGC": false
  },
  {
   "Case": "go",
   "Workers": 20,
   "ChanLen": 10000,
   "Amount": 1000,
   "SpentMs": 1825494,
   "AllocBytes": 945384,
   "AllocObjects": 7907,
   "AllocBytesTotal": 945384,
   "SystemMem": 2226424,
   "NoGC": false
  },
  {
   "Case": "go",
   "Workers": 20,
   "ChanLen": 10000,
   "Amount": 3000,
   "SpentMs": 5697802,
   "AllocBytes": 2381232,
   "AllocObjects": 23477,
   "AllocBytesTotal": 2666336,
   "SystemMem": 1900544,
   "NoGC": false
  },
  {
   "Case": "go",
   "Workers": 20,
   "ChanLen": 10000,
   "Amount": 10000,
   "SpentMs": 18304847,
   "AllocBytes": 1766872,
   "AllocObjects": 74750,
   "AllocBytesTotal": 7830400,
   "SystemMem": 3471608,
   "NoGC": false
  }
 ],
 "goweb": [
  {
   "Case": "goweb",
   "Workers": 20,
   "ChanLen": 10000,
   "Amount": 30,
   "SpentMs": 45011499,
   "AllocBytes": 935840,
   "AllocObjects": 4451,
   "AllocBytesTotal": 935840,
   "SystemMem": 3012856,
   "NoGC": false
  },
  {
   "Case": "goweb",
   "Workers": 20,
   "ChanLen": 10000,
   "Amount": 100,
   "SpentMs": 66730182,
   "AllocBytes": 2714952,
   "AllocObjects": 14006,
   "AllocBytesTotal": 2940808,
   "SystemMem": 2424832,
   "NoGC": false
  },
  {
   "Case": "goweb",
   "Workers": 20,
   "ChanLen": 10000,
   "Amount": 300,
   "SpentMs": 110317810,
   "AllocBytes": 6748336,
   "AllocObjects": 40591,
   "AllocBytesTotal": 8150832,
   "SystemMem": 4192504,
   "NoGC": false
  },
  {
   "Case": "goweb",
   "Workers": 20,
   "ChanLen": 10000,
   "Amount": 1000,
   "SpentMs": 164823320,
   "AllocBytes": 23886104,
   "AllocObjects": 132006,
   "AllocBytesTotal": 27476552,
   "SystemMem": 3014656,
   "NoGC": false
  },
  {
   "Case": "goweb",
   "Workers": 20,
   "ChanLen": 10000,
   "Amount": 3000,
   "SpentMs": 302782135,
   "AllocBytes": 73579856,
   "AllocObjects": 396182,
   "AllocBytesTotal": 79481896,
   "SystemMem": 74219768,
   "NoGC": false
  },
  {
   "Case": "goweb",
   "Workers": 20,
   "ChanLen": 10000,
   "Amount": 10000,
   "SpentMs": 677765781,
   "AllocBytes": 144205520,
   "AllocObjects": 1652236,
   "AllocBytesTotal": 229510344,
   "SystemMem": 217346296,
   "NoGC": false
  }
 ],
 "pool": [
  {
   "Case": "pool",
   "Workers": 20,
   "ChanLen": 10000,
   "Amount": 30,
   "SpentMs": 377819,
   "AllocBytes": 45736,
   "AllocObjects": 398,
   "AllocBytesTotal": 45736,
   "SystemMem": 524288,
   "NoGC": false
  },
  {
   "Case": "pool",
   "Workers": 20,
   "ChanLen": 10000,
   "Amount": 100,
   "SpentMs": 457498,
   "AllocBytes": 126312,
   "AllocObjects": 1017,
   "AllocBytesTotal": 126312,
   "SystemMem": 262144,
   "NoGC": false
  },
  {
   "Case": "pool",
   "Workers": 20,
   "ChanLen": 10000,
   "Amount": 300,
   "SpentMs": 814638,
   "AllocBytes": 354760,
   "AllocObjects": 2892,
   "AllocBytesTotal": 354760,
   "SystemMem": 262144,
   "NoGC": false
  },
  {
   "Case": "pool",
   "Workers": 20,
   "ChanLen": 10000,
   "Amount": 1000,
   "SpentMs": 1328993,
   "AllocBytes": 946192,
   "AllocObjects": 8457,
   "AllocBytesTotal": 946192,
   "SystemMem": 524288,
   "NoGC": false
  },
  {
   "Case": "pool",
   "Workers": 20,
   "ChanLen": 10000,
   "Amount": 3000,
   "SpentMs": 3645107,
   "AllocBytes": 2055648,
   "AllocObjects": 23311,
   "AllocBytesTotal": 2444888,
   "SystemMem": 2816248,
   "NoGC": false
  },
  {
   "Case": "pool",
   "Workers": 20,
   "ChanLen": 10000,
   "Amount": 10000,
   "SpentMs": 13022157,
   "AllocBytes": 2757408,
   "AllocObjects": 73234,
   "AllocBytesTotal": 7232168,
   "SystemMem": 3930360,
   "NoGC": false
  }
 ],
 "poolweb": [
  {
   "Case": "poolweb",
   "Workers": 20,
   "ChanLen": 10000,
   "Amount": 30,
   "SpentMs": 41682795,
   "AllocBytes": 798664,
   "AllocObjects": 3836,
   "AllocBytesTotal": 798664,
   "SystemMem": 2097152,
   "NoGC": false
  },
  {
   "Case": "poolweb",
   "Workers": 20,
   "ChanLen": 10000,
   "Amount": 100,
   "SpentMs": 122210890,
   "AllocBytes": 1404208,
   "AllocObjects": 9249,
   "AllocBytesTotal": 1404208,
   "SystemMem": 2097152,
   "NoGC": false
  },
  {
   "Case": "poolweb",
   "Workers": 20,
   "ChanLen": 10000,
   "Amount": 300,
   "SpentMs": 324544086,
   "AllocBytes": 1105480,
   "AllocObjects": 24874,
   "AllocBytesTotal": 3173392,
   "SystemMem": 2490368,
   "NoGC": false
  },
  {
   "Case": "poolweb",
   "Workers": 20,
   "ChanLen": 10000,
   "Amount": 1000,
   "SpentMs": 1033730828,
   "AllocBytes": 1119336,
   "AllocObjects": 80671,
   "AllocBytesTotal": 9290320,
   "SystemMem": 2490368,
   "NoGC": false
  },
  {
   "Case": "poolweb",
   "Workers": 20,
   "ChanLen": 10000,
   "Amount": 3000,
   "SpentMs": 3057527042,
   "AllocBytes": 1246880,
   "AllocObjects": 226658,
   "AllocBytesTotal": 24087776,
   "SystemMem": 3014656,
   "NoGC": false
  },
  {
   "Case": "poolweb",
   "Workers": 20,
   "ChanLen": 10000,
   "Amount": 10000,
   "SpentMs": 10133677954,
   "AllocBytes": 1294512,
   "AllocObjects": 747156,
   "AllocBytesTotal": 78112384,
   "SystemMem": 4454648,
   "NoGC": false
  }
 ]
}
